PyFFI-2.2.3.data/scripts/cgftoaster.py
PyFFI-2.2.3.data/scripts/kfmtoaster.py
PyFFI-2.2.3.data/scripts/nifmakehsl.py
PyFFI-2.2.3.data/scripts/niftoaster.py
PyFFI-2.2.3.data/scripts/patch_recursive_apply.py
PyFFI-2.2.3.data/scripts/patch_recursive_make.py
PyFFI-2.2.3.data/scripts/qskope.py
PyFFI-2.2.3.data/scripts/rockstar_pack_dir_img.py
PyFFI-2.2.3.data/scripts/rockstar_unpack_dir_img.py
pyffi/VERSION
pyffi/__init__.py
pyffi/formats/__init__.py
pyffi/formats/bsa/__init__.py
pyffi/formats/bsa/bsa.xml
pyffi/formats/cgf/__init__.py
pyffi/formats/cgf/cgf.xml
pyffi/formats/dae/COLLADASchema.xsd
pyffi/formats/dae/__init__.py
pyffi/formats/dds/__init__.py
pyffi/formats/dds/dds.xml
pyffi/formats/egm/__init__.py
pyffi/formats/egm/egm.xml
pyffi/formats/egt/__init__.py
pyffi/formats/egt/egt.xml
pyffi/formats/esp/__init__.py
pyffi/formats/esp/esp.xml
pyffi/formats/kfm/__init__.py
pyffi/formats/kfm/kfmxml/kfm.xml
pyffi/formats/nif/__init__.py
pyffi/formats/nif/nifxml/nif.xml
pyffi/formats/psk/__init__.py
pyffi/formats/psk/psk.xml
pyffi/formats/rockstar/__init__.py
pyffi/formats/rockstar/dir_/__init__.py
pyffi/formats/rockstar/dir_/dir.xml
pyffi/formats/tga/__init__.py
pyffi/formats/tga/tga.xml
pyffi/formats/tri/__init__.py
pyffi/formats/tri/tri.xml
pyffi/object_models/__init__.py
pyffi/object_models/any_type.py
pyffi/object_models/array_type.py
pyffi/object_models/binary_type.py
pyffi/object_models/common.py
pyffi/object_models/editable.py
pyffi/object_models/simple_type.py
pyffi/object_models/xml/__init__.py
pyffi/object_models/xml/array.py
pyffi/object_models/xml/basic.py
pyffi/object_models/xml/bit_struct.py
pyffi/object_models/xml/enum.py
pyffi/object_models/xml/expression.py
pyffi/object_models/xml/struct_.py
pyffi/object_models/xsd/__init__.py
pyffi/qskope/__init__.py
pyffi/qskope/detail_delegate.py
pyffi/qskope/detail_model.py
pyffi/qskope/detail_tree.py
pyffi/qskope/global_model.py
pyffi/qskope/global_tree.py
pyffi/spells/__init__.py
pyffi/spells/check.py
PyFFI-2.2.3.dist-info/LICENSE.rst
PyFFI-2.2.3.dist-info/METADATA
PyFFI-2.2.3.dist-info/WHEEL
PyFFI-2.2.3.dist-info/top_level.txt
PyFFI-2.2.3.dist-info/RECORD
