Metadata-Version: 2.1
Name: PyFFI
Version: 2.2.3
Summary: Processing block structured binary files.
Home-page: https://github.com/niftools/pyffi
Author: Niftools Developers
Author-email: info@niftools.org
License: UNKNOWN
Download-URL: https://github.com/niftools/pyffi/releases
Keywords: fileformat nif cgf binary interface stripify
Platform: UNKNOWN
Classifier: Development Status :: 4 - Beta
Classifier: License :: OSI Approved :: BSD License
Classifier: Intended Audience :: Developers
Classifier: Intended Audience :: End Users/Desktop
Classifier: Topic :: Multimedia :: Graphics :: 3D Modeling
Classifier: Programming Language :: Python
Classifier: Programming Language :: Python :: 3.3
Classifier: Programming Language :: Python :: 3.4
Classifier: Programming Language :: Python :: 3.5
Classifier: Programming Language :: Python :: 3.6
Classifier: Operating System :: OS Independent
Provides-Extra: doc
Provides-Extra: dev
